odoo/addons/ethiopic_calendar/README.rst
odoo/addons/ethiopic_calendar/__init__.py
odoo/addons/ethiopic_calendar/__manifest__.py
odoo/addons/ethiopic_calendar/models/__init__.py
odoo/addons/ethiopic_calendar/models/ethiopic_calendar.py
odoo/addons/ethiopic_calendar/models/pycalcal/COPYRIGHT_DERSHOWITZ_REINGOLD
odoo/addons/ethiopic_calendar/models/pycalcal/Install.md
odoo/addons/ethiopic_calendar/models/pycalcal/Readme.md
odoo/addons/ethiopic_calendar/models/pycalcal/STATUS
odoo/addons/ethiopic_calendar/models/pycalcal/astro.mp
odoo/addons/ethiopic_calendar/models/pycalcal/calendrica-3.0.cl
odoo/addons/ethiopic_calendar/models/pycalcal/calendrica-3.0.errata.cl
odoo/addons/ethiopic_calendar/models/pycalcal/dates1.tex
odoo/addons/ethiopic_calendar/models/pycalcal/dates2.tex
odoo/addons/ethiopic_calendar/models/pycalcal/dates3.tex
odoo/addons/ethiopic_calendar/models/pycalcal/dates4.tex
odoo/addons/ethiopic_calendar/models/pycalcal/dates5.errata.csv
odoo/addons/ethiopic_calendar/models/pycalcal/dates5.tex
odoo/addons/ethiopic_calendar/models/pycalcal/errata20091115.pdf
odoo/addons/ethiopic_calendar/models/pycalcal/errata20091119.pdf
odoo/addons/ethiopic_calendar/models/pycalcal/errata20091230.pdf
odoo/addons/ethiopic_calendar/models/pycalcal/errata20110623.pdf
odoo/addons/ethiopic_calendar/models/pycalcal/errata20130806.pdf
odoo/addons/ethiopic_calendar/models/pycalcal/fig_alt-az.asy
odoo/addons/ethiopic_calendar/models/pycalcal/fig_alt-az.png
odoo/addons/ethiopic_calendar/models/pycalcal/fig_coord_transform.gv
odoo/addons/ethiopic_calendar/models/pycalcal/fig_coord_transform.png
odoo/addons/ethiopic_calendar/models/pycalcal/fig_ecliptic.mp
odoo/addons/ethiopic_calendar/models/pycalcal/fig_ra-dec.mp
odoo/addons/ethiopic_calendar/models/pycalcal/makemake.sh
odoo/addons/ethiopic_calendar/models/pycalcal/pycalcal.bib
odoo/addons/ethiopic_calendar/models/pycalcal/pycalcal.nw
odoo/addons/ethiopic_calendar/models/pycalcal/pycalcal.pdf
odoo14_addon_ethiopic_calendar-14.0.1.0.1.dev3.dist-info/METADATA
odoo14_addon_ethiopic_calendar-14.0.1.0.1.dev3.dist-info/WHEEL
odoo14_addon_ethiopic_calendar-14.0.1.0.1.dev3.dist-info/top_level.txt
odoo14_addon_ethiopic_calendar-14.0.1.0.1.dev3.dist-info/RECORD
