Metadata-Version: 2.1
Name: odoo14-addon-ethiopic_calendar
Version: 14.0.1.0.1.dev3
Summary: Date calculations in the Ethiopian calendar
Home-page: https://github.com/trevi-software/trevi-hr
Author: TREVI Software, Michael Telahun Makonnen
License: AGPL-3
Classifier: Programming Language :: Python
Classifier: Framework :: Odoo
Classifier: Framework :: Odoo :: 14.0
Classifier: License :: OSI Approved :: GNU Affero General Public License v3
Requires-Python: >=3.6
Requires-Dist: mpmath
Requires-Dist: odoo<14.1dev,>=14.0a
